LICENSE.txt
MANIFEST.in
README.rst
setup.py
semester/__init__.py
semester/__main__.py
semester/assignments.py
semester/figures.py
semester/grades.py
semester/pytem.py
semester/roster.py
semester.egg-info/PKG-INFO
semester.egg-info/SOURCES.txt
semester.egg-info/dependency_links.txt
semester.egg-info/entry_points.txt
semester.egg-info/top_level.txt
semester/init/__init__.py
semester/init/__main__.py
semester/init/makeoutput.py
semester/init/makeweb.py
semester/init/newsemester.py
semester/init/newsemgui.py
semester/init/src/syllabus.tex
semester/util/__init__.py
semester/util/canvasgrader.py