Metadata-Version: 1.1
Name: semester
Version: 0.1.0
Summary: Tools to help with running a semester based course
Home-page: http://semester.readthedocs.org
Author: Henry Schreiner
Author-email: henryiii@physics.utexas.edu
License: MIT
Keywords: classes,teaching,grading,exam,lab,course,school
Platform: POSIX
Platform: Windows
Classifier: Development Status :: 2 - Pre-Alpha
Classifier: License :: OSI Approved :: MIT License
Classifier: Operating System :: Microsoft :: Windows
Classifier: Operating System :: POSIX
Classifier: Programming Language :: Python :: 2.7
Classifier: Programming Language :: Python :: 3
Classifier: Programming Language :: Python :: 3.3
Classifier: Programming Language :: Python :: 3.4
Classifier: Programming Language :: Python :: 3.5
Classifier: Topic :: Software Development :: Build Tools
Classifier: Topic :: System :: Systems Administration
Provides: semester
